DijkstraAlgo.py
DijkstraAlgo-0.0.7.dist-info/LICENSE
DijkstraAlgo-0.0.7.dist-info/METADATA
DijkstraAlgo-0.0.7.dist-info/WHEEL
DijkstraAlgo-0.0.7.dist-info/top_level.txt
DijkstraAlgo-0.0.7.dist-info/RECORD
