Metadata-Version: 2.1
Name: DijkstraAlgo
Version: 0.0.7
Summary: To measure the shortest distance of any nodes or any particular points, we can use this package.
Home-page: https://github.com/MizanMustakim/DijkstraAlgo-Package
Author: Md Mizanur Rahman Mustakim
Author-email: mustakim.mizan@gmail.com
License: UNKNOWN
Download-URL: https://github.com/MizanMustakim/DijkstraAlgo-Package/archive/0.0.7.tar.gz
Keywords: Shortest Path,Dijkstra Algorithm,Graph,Shortest Distance,Shortest Route,Dijkstra_2D,Dijkstra_3D
Platform: UNKNOWN
Classifier: Development Status :: 4 - Beta
Classifier: Intended Audience :: Developers
Classifier: License :: OSI Approved :: GNU General Public License v2 or later (GPLv2+)
Classifier: Operating System :: OS Independent
Classifier: Programming Language :: Python :: 3
Classifier: Programming Language :: Python :: 3.5
Classifier: Programming Language :: Python :: 3.6
Classifier: Programming Language :: Python :: 3.7
Classifier: Programming Language :: Python :: 3.8
Classifier: Operating System :: OS Independent
Provides-Extra: dev
Requires-Dist: pytest (>=3.7) ; extra == 'dev'
